poetry_stickywheel_plugin.py
poetry_stickywheel_plugin-0.2.0.dist-info/METADATA
poetry_stickywheel_plugin-0.2.0.dist-info/WHEEL
poetry_stickywheel_plugin-0.2.0.dist-info/entry_points.txt
poetry_stickywheel_plugin-0.2.0.dist-info/RECORD
