Metadata-Version: 2.1
Name: poetry-stickywheel-plugin
Version: 0.2.0
Summary: 
Author: Daniel Knell
Author-email: contact@danielknell.co.uk
Requires-Python: >=3.8,<4.0
Classifier: Programming Language :: Python :: 3
Classifier: Programming Language :: Python :: 3.8
Classifier: Programming Language :: Python :: 3.9
Classifier: Programming Language :: Python :: 3.10
Classifier: Programming Language :: Python :: 3.11
Classifier: Programming Language :: Python :: 3.12
Requires-Dist: poetry (>=1.2,<2.0)
